cpyMSpec_0_3_5/__init__.py
cpyMSpec_0_3_5/ims.h
cpyMSpec_0_3_5/legacy_interface.py
cpyMSpec_0_3_5/libms_cffi_0_3_5.so
cpyMSpec_0_3_5/spectrum.py
cpyMSpec_0_3_5/utils.py
cpyMSpec_0_3_5-0.3.5.dist-info/LICENSE
cpyMSpec_0_3_5-0.3.5.dist-info/METADATA
cpyMSpec_0_3_5-0.3.5.dist-info/WHEEL
cpyMSpec_0_3_5-0.3.5.dist-info/top_level.txt
cpyMSpec_0_3_5-0.3.5.dist-info/RECORD
