Metadata-Version: 2.1
Name: cpyMSpec-0-3-5
Version: 0.3.5
Summary: isotope pattern calculator for small molecules
Home-page: https://github.com/alexandrovteam/cpyMSpec
Author: Artem Tarasov
Author-email: artem.tarasov@embl.de
License: Apache 2.0
Platform: UNKNOWN
Classifier: Development Status :: 5 - Production/Stable
Classifier: Intended Audience :: Science/Research
Classifier: License :: OSI Approved :: Apache Software License
Classifier: Topic :: Scientific/Engineering :: Bio-Informatics
Requires-Dist: cffi (>=1.7)
